hyabsa/__cli__.py
hyabsa/__init__.py
hyabsa/_version.py
hyabsa/agents/__init__.py
hyabsa/agents/absa.py
hyabsa/agents/base.py
hyabsa/agents/results.py
hyabsa/conf/__init__.py
hyabsa/conf/about/hyabsa.yaml
hyabsa/conf/agent/__init__.yaml
hyabsa/conf/agent/absa.yaml
hyabsa/conf/agent/gpt4.yaml
hyabsa/conf/llm/__init__.yaml
hyabsa/conf/llm/gpt35.yaml
hyabsa/conf/llm/gpt4.yaml
hyabsa/conf/llm/openai.yaml
hyabsa/conf/pipe/convert_absa_output_to_results.yaml
hyabsa/conf/prompts/__help__.yaml
hyabsa/conf/prompts/__init__.yaml
hyabsa/conf/prompts/default.yaml
hyabsa/conf/run/convert_absa_output_to_results.yaml
hyabsa/conf/runner/absa.yaml
hyabsa/conf/runner/gpt4.yaml
hyabsa/contexts/__init__.py
hyabsa/llms/__init__.py
hyabsa/llms/openai.py
hyabsa/prompts/__init__.py
hyabsa/py.typed
hyabsa/runners/__init__.py
hyabsa/runners/absa.py
hyfi_absa-0.5.1.dist-info/LICENSE
hyfi_absa-0.5.1.dist-info/METADATA
hyfi_absa-0.5.1.dist-info/WHEEL
hyfi_absa-0.5.1.dist-info/entry_points.txt
hyfi_absa-0.5.1.dist-info/RECORD
