Metadata-Version: 2.1
Name: hyfi-absa
Version: 0.5.1
Summary: HyFI-ABSA is a Python package developed as a plugin for the Hydra Fast Interface (HyFI).
Home-page: https://hyfi-absa.entelecheia.ai
License: MIT
Author: Young Joon Lee
Author-email: entelecheia@hotmail.com
Requires-Python: >=3.9,<3.13
Classifier: License :: OSI Approved :: MIT License
Classifier: Programming Language :: Python :: 3
Classifier: Programming Language :: Python :: 3.9
Classifier: Programming Language :: Python :: 3.10
Classifier: Programming Language :: Python :: 3.11
Classifier: Programming Language :: Python :: 3.12
Requires-Dist: click (>=8.1.3,<9.0.0)
Requires-Dist: hyfi (>=1.36.3,<2.0.0)
Requires-Dist: openai (>=1.0.0,<1.15.0)
Requires-Dist: tenacity (>=8.2.3,<9.0.0)
Project-URL: Repository, https://github.com/entelecheia/hyfi-absa
